[
  {
    "name": "Jimmybowman",
    "realm": "Nordanaar",
    "level": 27,
    "race": "Troll",
    "class": "Hunter",
    "skills": {
      "Cooking": 90,
      "First Aid": 2,
      "Fishing": 107,
      "Leatherworking": 60,
      "Skinning": 207,
      "Survival": 54,
      "Mining": 73
    }
  },
  {
    "name": "Rizziopea",
    "realm": "Nordanaar",
    "level": 25,
    "race": "Troll",
    "class": "Priest",
    "skills": {
      "Enchanting": 120,
      "Fishing": 1,
      "Survival": 51,
      "Tailoring": 123
    }
  },
  {
    "name": "Nallesham",
    "realm": "Nordanaar",
    "level": 27,
    "race": "Tauren",
    "class": "Shaman",
    "skills": {
      "First Aid": 1,
      "Fishing": 81,
      "Mining": 122,
      "Survival": 57
    }
  },
  {
    "name": "Kaleighh",
    "realm": "Nordanaar",
    "level": 25,
    "race": "Undead",
    "class": "Warlock",
    "skills": {
      "Fishing": 1,
      "Engineering": 67,
      "Mining": 58,
      "First Aid": 1
    }
  },
  {
    "name": "Nutby",
    "realm": "Nordanaar",
    "level": 27,
    "race": "Tauren",
    "class": "Druid",
    "skills": {
      "Alchemy": 180,
      "Cooking": 53,
      "First Aid": 83,
      "Fishing": 132,
      "Herbalism": 159,
      "Survival": 55
    }
  },
  {
    "name": "Pissgoblin",
    "realm": "Nordanaar",
    "level": 13,
    "race": "Goblin",
    "class": "Mage",
    "skills": {
      "Cooking": 1,
      "Engineering": 1,
      "First Aid": 46,
      "Fishing": 78,
      "Herbalism": 19,
      "Mining": 14
    }
  },
  {
    "name": "Nallebones",
    "realm": "Nordanaar",
    "level": 14,
    "race": "Undead",
    "class": "Warrior",
    "skills": {
      "Blacksmithing": 57,
      "First Aid": 3,
      "Fishing": 4,
      "Mining": 57
    }
  },
  {
    "name": "Jimmystabman",
    "realm": "Nordanaar",
    "level": 6,
    "race": "Night Elf",
    "class": "Rogue"
  },
  {
    "name": "Nalledin",
    "realm": "Nordanaar",
    "level": 5,
    "race": 10,
    "class": "Paladin"
  },
  {
    "name": "Profil",
    "realm": "Nordanaar",
    "level": 6,
    "race": "Dwarf",
    "class": "Paladin"
  },
  {
    "name": "Vallina",
    "realm": "Nordanaar",
    "level": 5,
    "race": 10,
    "class": "Paladin"
  },
  {
    "name": "Rogueface",
    "realm": "Nordanaar",
    "level": 8,
    "race": "Troll",
    "class": "Rogue",
    "skills": {
      "Fishing": 1,
      "Mining": 1,
      "Engineering": 1
    }
  },
  {
    "name": "Rokora",
    "realm": "Nordanaar",
    "level": 14,
    "race": "Orc",
    "class": "Warrior",
    "skills": {
      "Blacksmithing": 55,
      "First Aid": 60,
      "Mining": 61,
      "Cooking": 55,
      "Fishing": 15
    }
  }
]
